MANIFEST.in
README.txt
setup.cfg
setup.py
scribes/__init__.py
scribes.helpers.egg-info/PKG-INFO
scribes.helpers.egg-info/SOURCES.txt
scribes.helpers.egg-info/dependency_links.txt
scribes.helpers.egg-info/namespace_packages.txt
scribes.helpers.egg-info/not-zip-safe
scribes.helpers.egg-info/requires.txt
scribes.helpers.egg-info/top_level.txt
scribes/helpers/__init__.py
scribes/helpers/signals.py