Metadata-Version: 1.0
Name: scribes.helpers
Version: 0.5.1
Summary: Wrappers for easy scribes plugins development
Home-page: http://github.com/baverman/scribes-goodies
Author: Anton Bobrov
Author-email: bobrov@vl.ru
License: UNKNOWN
Platform: UNKNOWN
